[{"OBJECTID_1":1,"OBJECTID":1,"CCDD":"01","NOMBDEP":"AMAZONAS","CAPITAL":"CHACHAPOYAS","Shape_STAr":3.20300632441,"Shape_STLe":12.9120882058,"ORIG_FID":0,"Shape_Leng":12.9120882036,"Shape_Area":3.20300632441,"CORREO":"juan.suyo@geogpsperu.com","CONTACTO":"www.geogpsperu.com","WHATSAPP":"931381206"},{"OBJECTID_1":2,"OBJECTID":2,"CCDD":"02","NOMBDEP":"ANCASH","CAPITAL":"HUARAZ","Shape_STAr":2.95459163492,"Shape_STLe":11.7804235112,"ORIG_FID":1,"Shape_Leng":11.780423513,"Shape_Area":2.95459163495,"CORREO":"juan.suyo@geogpsperu.com","CONTACTO":"www.geogpsperu.com","WHATSAPP":"931381206"},{"OBJECTID_1":3,"OBJECTID":3,"CCDD":"03","NOMBDEP":"APURIMAC","CAPITAL":"ABANCAY","Shape_STAr":1.76593309446,"Shape_STLe":7.73015446001,"ORIG_FID":2,"Shape_Leng":7.73015445565,"Shape_Area":1.76593309444,"CORREO":"juan.suyo@geogpsperu.com","CONTACTO":"www.geogpsperu.com","WHATSAPP":"931381206"},{"OBJECTID_1":4,"OBJECTID":4,"CCDD":"04","NOMBDEP":"AREQUIPA","CAPITAL":"AREQUIPA","Shape_STAr":5.33020323722,"Shape_STLe":17.4050401699,"ORIG_FID":3,"Shape_Leng":17.4050401679,"Shape_Area":5.33020323716,"CORREO":"juan.suyo@geogpsperu.com","CONTACTO":"www.geogpsperu.com","WHATSAPP":"931381206"},{"OBJECTID_1":5,"OBJECTID":5,"CCDD":"05","NOMBDEP":"AYACUCHO","CAPITAL":"AYACUCHO","Shape_STAr":3.64370528801,"Shape_STLe":17.1271662044,"ORIG_FID":4,"Shape_Leng":17.1271662058,"Shape_Area":3.64370528801,"CORREO":"juan.suyo@geogpsperu.com","CONTACTO":"www.geogpsperu.com","WHATSAPP":"931381206"},{"OBJECTID_1":6,"OBJECTID":6,"CCDD":"06","NOMBDEP":"CAJAMARCA","CAPITAL":"CAJAMARCA","Shape_STAr":2.68452725731,"Shape_STLe":12.3974244921,"ORIG_FID":5,"Shape_Leng":12.3974244944,"Shape_Area":2.68452725725,"CORREO":"juan.suyo@geogpsperu.com","CONTACTO":"www.geogpsperu.com","WHATSAPP":"931381206"},{"OBJECTID_1":7,"OBJECTID":7,"CCDD":"07","NOMBDEP":"CALLAO","CAPITAL":"CALLAO","Shape_STAr":0.011738237733,"Shape_STLe":1.11122087561,"ORIG_FID":6,"Shape_Leng":1.11122087596,"Shape_Area":0.0117382377391,"CORREO":"juan.suyo@geogpsperu.com","CONTACTO":"www.geogpsperu.com","WHATSAPP":"931381206"},{"OBJECTID_1":8,"OBJECTID":8,"CCDD":"08","NOMBDEP":"CUSCO","CAPITAL":"CUSCO","Shape_STAr":6.00033138589,"Shape_STLe":21.794434089,"ORIG_FID":7,"Shape_Leng":21.7944340977,"Shape_Area":6.00033138591,"CORREO":"juan.suyo@geogpsperu.com","CONTACTO":"www.geogpsperu.com","WHATSAPP":"931381206"},{"OBJECTID_1":9,"OBJECTID":9,"CCDD":"09","NOMBDEP":"HUANCAVELICA","CAPITAL":"HUANCAVELICA","Shape_STAr":1.83985138786,"Shape_STLe":9.56124524736,"ORIG_FID":8,"Shape_Leng":9.56124525763,"Shape_Area":1.83985138783,"CORREO":"juan.suyo@geogpsperu.com","CONTACTO":"www.geogpsperu.com","WHATSAPP":"931381206"},{"OBJECTID_1":10,"OBJECTID":10,"CCDD":"10","NOMBDEP":"HUANUCO","CAPITAL":"HUANUCO","Shape_STAr":3.08981093626,"Shape_STLe":14.5898401996,"ORIG_FID":9,"Shape_Leng":14.5898401893,"Shape_Area":3.08981093618,"CORREO":"juan.suyo@geogpsperu.com","CONTACTO":"www.geogpsperu.com","WHATSAPP":"931381206"},{"OBJECTID_1":11,"OBJECTID":11,"CCDD":"11","NOMBDEP":"ICA","CAPITAL":"ICA","Shape_STAr":1.76702547213,"Shape_STLe":10.3743676198,"ORIG_FID":10,"Shape_Leng":10.3743676116,"Shape_Area":1.76702547215,"CORREO":"juan.suyo@geogpsperu.com","CONTACTO":"www.geogpsperu.com","WHATSAPP":"931381206"},{"OBJECTID_1":12,"OBJECTID":12,"CCDD":"12","NOMBDEP":"JUNIN","CAPITAL":"HUANCAYO","Shape_STAr":3.6588810974,"Shape_STLe":14.3147267548,"ORIG_FID":11,"Shape_Leng":14.3147267518,"Shape_Area":3.6588810974,"CORREO":"juan.suyo@geogpsperu.com","CONTACTO":"www.geogpsperu.com","WHATSAPP":"931381206"},{"OBJECTID_1":13,"OBJECTID":13,"CCDD":"13","NOMBDEP":"LA LIBERTAD","CAPITAL":"TRUJILLO","Shape_STAr":2.06877996357,"Shape_STLe":13.1482657924,"ORIG_FID":12,"Shape_Leng":13.1482657792,"Shape_Area":2.06877996353,"CORREO":"juan.suyo@geogpsperu.com","CONTACTO":"www.geogpsperu.com","WHATSAPP":"931381206"},{"OBJECTID_1":14,"OBJECTID":14,"CCDD":"14","NOMBDEP":"LAMBAYEQUE","CAPITAL":"CHICLAYO","Shape_STAr":1.18499432836,"Shape_STLe":6.68535112495,"ORIG_FID":13,"Shape_Leng":6.68535111746,"Shape_Area":1.18499432835,"CORREO":"juan.suyo@geogpsperu.com","CONTACTO":"www.geogpsperu.com","WHATSAPP":"931381206"},{"OBJECTID_1":15,"OBJECTID":15,"CCDD":"15","NOMBDEP":"LIMA","CAPITAL":"LIMA","Shape_STAr":2.9044749278,"Shape_STLe":12.7452261965,"ORIG_FID":14,"Shape_Leng":12.7452262255,"Shape_Area":2.90447492781,"CORREO":"juan.suyo@geogpsperu.com","CONTACTO":"www.geogpsperu.com","WHATSAPP":"931381206"},{"OBJECTID_1":19,"OBJECTID":16,"CCDD":"16","NOMBDEP":"LORETO","CAPITAL":"IQUITOS","Shape_STAr":30.550256087,"Shape_STLe":46.7017889135,"ORIG_FID":15,"Shape_Leng":46.7017889113,"Shape_Area":30.5502560871,"CORREO":"juan.suyo@geogpsperu.com","CONTACTO":"www.geogpsperu.com","WHATSAPP":"931381206"},{"OBJECTID_1":20,"OBJECTID":17,"CCDD":"17","NOMBDEP":"MADRE DE DIOS","CAPITAL":"PUERTO MALDONADO","Shape_STAr":7.02385368277,"Shape_STLe":15.416397151,"ORIG_FID":16,"Shape_Leng":15.4163971679,"Shape_Area":7.02385368312,"CORREO":"juan.suyo@geogpsperu.com","CONTACTO":"www.geogpsperu.com","WHATSAPP":"931381206"},{"OBJECTID_1":21,"OBJECTID":18,"CCDD":"18","NOMBDEP":"MOQUEGUA","CAPITAL":"MOQUEGUA","Shape_STAr":1.33488793705,"Shape_STLe":7.72042387698,"ORIG_FID":17,"Shape_Leng":7.72042387129,"Shape_Area":1.33488793705,"CORREO":"juan.suyo@geogpsperu.com","CONTACTO":"www.geogpsperu.com","WHATSAPP":"931381206"},{"OBJECTID_1":22,"OBJECTID":19,"CCDD":"19","NOMBDEP":"PASCO","CAPITAL":"CERRO DE PASCO","Shape_STAr":1.97286382441,"Shape_STLe":10.8916977758,"ORIG_FID":18,"Shape_Leng":10.8916977696,"Shape_Area":1.97286382442,"CORREO":"juan.suyo@geogpsperu.com","CONTACTO":"www.geogpsperu.com","WHATSAPP":"931381206"},{"OBJECTID_1":23,"OBJECTID":20,"CCDD":"20","NOMBDEP":"PIURA","CAPITAL":"PIURA","Shape_STAr":2.89922289074,"Shape_STLe":11.2994707345,"ORIG_FID":19,"Shape_Leng":11.2994707354,"Shape_Area":2.89922289077,"CORREO":"juan.suyo@geogpsperu.com","CONTACTO":"www.geogpsperu.com","WHATSAPP":"931381206"},{"OBJECTID_1":24,"OBJECTID":21,"CCDD":"21","NOMBDEP":"PUNO","CAPITAL":"PUNO","Shape_STAr":5.66668401616,"Shape_STLe":26.7097212172,"ORIG_FID":20,"Shape_Leng":26.7097212043,"Shape_Area":5.66668401586,"CORREO":"juan.suyo@geogpsperu.com","CONTACTO":"www.geogpsperu.com","WHATSAPP":"931381206"},{"OBJECTID_1":31,"OBJECTID":22,"CCDD":"22","NOMBDEP":"SAN MARTIN","CAPITAL":"MOYOBAMBA","Shape_STAr":4.17466434975,"Shape_STLe":16.1629535554,"ORIG_FID":21,"Shape_Leng":16.1629535483,"Shape_Area":4.17466434971,"CORREO":"juan.suyo@geogpsperu.com","CONTACTO":"www.geogpsperu.com","WHATSAPP":"931381206"},{"OBJECTID_1":32,"OBJECTID":23,"CCDD":"23","NOMBDEP":"TACNA","CAPITAL":"TACNA","Shape_STAr":1.3620216238,"Shape_STLe":6.08870360157,"ORIG_FID":22,"Shape_Leng":6.08870359537,"Shape_Area":1.36202162376,"CORREO":"juan.suyo@geogpsperu.com","CONTACTO":"www.geogpsperu.com","WHATSAPP":"931381206"},{"OBJECTID_1":33,"OBJECTID":24,"CCDD":"24","NOMBDEP":"TUMBES","CAPITAL":"TUMBES","Shape_STAr":0.378756630572,"Shape_STLe":3.78797701255,"ORIG_FID":23,"Shape_Leng":3.78797702721,"Shape_Area":0.378756630581,"CORREO":"juan.suyo@geogpsperu.com","CONTACTO":"www.geogpsperu.com","WHATSAPP":"931381206"},{"OBJECTID_1":34,"OBJECTID":25,"CCDD":"25","NOMBDEP":"UCAYALI","CAPITAL":"PUCALLPA","Shape_STAr":8.66011056349,"Shape_STLe":27.4701592924,"ORIG_FID":24,"Shape_Leng":27.4701592867,"Shape_Area":8.66011056354,"CORREO":"juan.suyo@geogpsperu.com","CONTACTO":"www.geogpsperu.com","WHATSAPP":"931381206"}]